__builtins__.py
everysk/__init__.py
everysk/config.py
everysk/config.pyi
everysk/settings.py
everysk/tests.py
everysk/utils.py
everysk/api/__init__.py
everysk/api/api_requestor.py
everysk/api/http_client.py
everysk/api/tests.py
everysk/api/utils.py
everysk/api/_tests/api_requestor.py
everysk/api/_tests/http_client.py
everysk/api/_tests/init.py
everysk/api/_tests/utils.py
everysk/api/api_resources/__init__.py
everysk/api/api_resources/api_resource.py
everysk/api/api_resources/calculation.py
everysk/api/api_resources/custom_index.py
everysk/api/api_resources/datastore.py
everysk/api/api_resources/file.py
everysk/api/api_resources/market_data.py
everysk/api/api_resources/parser.py
everysk/api/api_resources/portfolio.py
everysk/api/api_resources/private_security.py
everysk/api/api_resources/report.py
everysk/api/api_resources/report_template.py
everysk/api/api_resources/tests.py
everysk/api/api_resources/worker_execution.py
everysk/api/api_resources/workflow.py
everysk/api/api_resources/workflow_execution.py
everysk/api/api_resources/workspace.py
everysk/api/api_resources/_tests/api_resource.py
everysk/api/api_resources/_tests/calculation.py
everysk/api/api_resources/_tests/custom_index.py
everysk/api/api_resources/_tests/datastore.py
everysk/api/api_resources/_tests/file.py
everysk/api/api_resources/_tests/market_data.py
everysk/api/api_resources/_tests/parser.py
everysk/api/api_resources/_tests/portfolio.py
everysk/api/api_resources/_tests/private_security.py
everysk/api/api_resources/_tests/report.py
everysk/api/api_resources/_tests/report_template.py
everysk/api/api_resources/_tests/worker_execution.py
everysk/api/api_resources/_tests/workflow.py
everysk/api/api_resources/_tests/workflow_execution.py
everysk/api/api_resources/_tests/workspace.py
everysk/core/compress.py
everysk/core/exceptions.py
everysk/core/fields.py
everysk/core/firestore.py
everysk/core/http.py
everysk/core/lists.py
everysk/core/log.py
everysk/core/number.py
everysk/core/object.py
everysk_beta-1.6.1459.dist-info/.gitignore
everysk_beta-1.6.1459.dist-info/LICENSE.txt
everysk_beta-1.6.1459.dist-info/METADATA
everysk_beta-1.6.1459.dist-info/WHEEL
everysk_beta-1.6.1459.dist-info/top_level.txt
everysk_beta-1.6.1459.dist-info/RECORD
