Metadata-Version: 2.2
Name: everysk-beta
Version: 1.6.1459
Summary: Generic lib to share python code on Everysk.
License: (C) Copyright 2023 EVERYSK TECHNOLOGIES
Project-URL: Homepage, https://everysk.com/
Keywords: python,setuptools,development,lib
Classifier: Development Status :: 4 - Beta
Classifier: Intended Audience :: Developers
Classifier: Topic :: Software Development :: Build Tools
Classifier: Programming Language :: Python :: 3.11
Requires-Python: >=3.11
License-File: LICENSE.txt
Requires-Dist: python-dateutil==2.8.2
Requires-Dist: holidays==0.51
Requires-Dist: tzdata==2024.1
Provides-Extra: requests
Requires-Dist: certifi==2024.2.2; extra == "requests"
Requires-Dist: charset-normalizer==3.3.2; extra == "requests"
Requires-Dist: idna==3.6; extra == "requests"
Requires-Dist: urllib3==2.2.1; extra == "requests"
Requires-Dist: requests==2.31.0; extra == "requests"
Provides-Extra: firestore
Requires-Dist: certifi==2024.2.2; extra == "firestore"
Requires-Dist: charset-normalizer==3.3.2; extra == "firestore"
Requires-Dist: idna==3.6; extra == "firestore"
Requires-Dist: urllib3==2.2.1; extra == "firestore"
Requires-Dist: requests==2.31.0; extra == "firestore"
Requires-Dist: pyasn1==0.5.1; extra == "firestore"
Requires-Dist: pyasn1-modules==0.3.0; extra == "firestore"
Requires-Dist: cachetools==5.3.2; extra == "firestore"
Requires-Dist: rsa==4.9; extra == "firestore"
Requires-Dist: google-auth==2.28.1; extra == "firestore"
Requires-Dist: googleapis-common-protos==1.62.0; extra == "firestore"
Requires-Dist: grpcio==1.60.1; extra == "firestore"
Requires-Dist: grpcio-status==1.60.1; extra == "firestore"
Requires-Dist: google-api-core[grpc]==2.17.1; extra == "firestore"
Requires-Dist: google-cloud-core==2.4.1; extra == "firestore"
Requires-Dist: proto-plus==1.23.0; extra == "firestore"
Requires-Dist: protobuf==4.25.3; extra == "firestore"
Requires-Dist: google-cloud-firestore==2.15.0; extra == "firestore"
Provides-Extra: redis
Requires-Dist: redis==5.0.8; extra == "redis"
Provides-Extra: tasks
Requires-Dist: certifi==2024.2.2; extra == "tasks"
Requires-Dist: charset-normalizer==3.3.2; extra == "tasks"
Requires-Dist: idna==3.6; extra == "tasks"
Requires-Dist: urllib3==2.2.1; extra == "tasks"
Requires-Dist: requests==2.31.0; extra == "tasks"
Requires-Dist: pyasn1==0.5.1; extra == "tasks"
Requires-Dist: pyasn1-modules==0.3.0; extra == "tasks"
Requires-Dist: cachetools==5.3.2; extra == "tasks"
Requires-Dist: rsa==4.9; extra == "tasks"
Requires-Dist: google-auth==2.28.1; extra == "tasks"
Requires-Dist: googleapis-common-protos==1.62.0; extra == "tasks"
Requires-Dist: grpcio==1.60.1; extra == "tasks"
Requires-Dist: grpcio-status==1.60.1; extra == "tasks"
Requires-Dist: google-api-core[grpc]==2.17.1; extra == "tasks"
Requires-Dist: google-cloud-core==2.4.1; extra == "tasks"
Requires-Dist: proto-plus==1.23.0; extra == "tasks"
Requires-Dist: protobuf==4.25.3; extra == "tasks"
Requires-Dist: grpc-google-iam-v1==0.13.0; extra == "tasks"
Requires-Dist: google-cloud-tasks==2.16.1; extra == "tasks"
Provides-Extra: flask
Requires-Dist: MarkupSafe==2.1.5; extra == "flask"
Requires-Dist: blinker==1.8.2; extra == "flask"
Requires-Dist: click==8.1.7; extra == "flask"
Requires-Dist: itsdangerous==2.2.0; extra == "flask"
Requires-Dist: Jinja2==3.1.4; extra == "flask"
Requires-Dist: Werkzeug==3.0.3; extra == "flask"
Requires-Dist: flask==3.0.3; extra == "flask"
Provides-Extra: starlette
Requires-Dist: idna==3.6; extra == "starlette"
Requires-Dist: sniffio==1.3.1; extra == "starlette"
Requires-Dist: anyio==4.4.0; extra == "starlette"
Requires-Dist: certifi==2024.2.2; extra == "starlette"
Requires-Dist: h11==0.14.0; extra == "starlette"
Requires-Dist: httpcore==1.0.5; extra == "starlette"
Requires-Dist: itsdangerous==2.2.0; extra == "starlette"
Requires-Dist: MarkupSafe==2.1.5; extra == "starlette"
Requires-Dist: Jinja2==3.1.4; extra == "starlette"
Requires-Dist: python-multipart==0.0.9; extra == "starlette"
Requires-Dist: pyyaml==6.0.2; extra == "starlette"
Requires-Dist: starlette==0.38.2; extra == "starlette"
Requires-Dist: hpack==4.0.0; extra == "starlette"
Requires-Dist: hyperframe==6.0.1; extra == "starlette"
Requires-Dist: h2==4.1.0; extra == "starlette"
Requires-Dist: httpx==0.27.2; extra == "starlette"
Requires-Dist: priority==2.0.0; extra == "starlette"
Requires-Dist: uvloop==0.20.0; extra == "starlette"
Requires-Dist: wsproto==1.2.0; extra == "starlette"
Requires-Dist: Hypercorn==0.17.3; extra == "starlette"
Provides-Extra: httpx
Requires-Dist: idna==3.6; extra == "httpx"
Requires-Dist: sniffio==1.3.1; extra == "httpx"
Requires-Dist: anyio==4.4.0; extra == "httpx"
Requires-Dist: certifi==2024.2.2; extra == "httpx"
Requires-Dist: h11==0.14.0; extra == "httpx"
Requires-Dist: httpcore==1.0.5; extra == "httpx"
Requires-Dist: hpack==4.0.0; extra == "httpx"
Requires-Dist: hyperframe==6.0.1; extra == "httpx"
Requires-Dist: h2==4.1.0; extra == "httpx"
Requires-Dist: httpx==0.27.2; extra == "httpx"
Provides-Extra: paramiko
Requires-Dist: bcrypt==4.2.0; extra == "paramiko"
Requires-Dist: pycparser==2.22; extra == "paramiko"
Requires-Dist: cffi==1.17.1; extra == "paramiko"
Requires-Dist: cryptography==43.0.3; extra == "paramiko"
Requires-Dist: pynacl==1.5.0; extra == "paramiko"
Requires-Dist: paramiko==3.5.0; extra == "paramiko"
